config/__init__.py
config/conftest.py
pytestCollectInfoPlugin-1.0.6.dist-info/METADATA
pytestCollectInfoPlugin-1.0.6.dist-info/WHEEL
pytestCollectInfoPlugin-1.0.6.dist-info/top_level.txt
pytestCollectInfoPlugin-1.0.6.dist-info/RECORD
